odoo/addons/crm_stage_type/README.rst
odoo/addons/crm_stage_type/__init__.py
odoo/addons/crm_stage_type/__manifest__.py
odoo/addons/crm_stage_type/i18n/crm_stage_type.pot
odoo/addons/crm_stage_type/i18n/sl.po
odoo/addons/crm_stage_type/models/__init__.py
odoo/addons/crm_stage_type/models/crm_lead.py
odoo/addons/crm_stage_type/models/crm_stage.py
odoo/addons/crm_stage_type/readme/CONTRIBUTORS.rst
odoo/addons/crm_stage_type/readme/DESCRIPTION.rst
odoo/addons/crm_stage_type/static/description/icon.png
odoo/addons/crm_stage_type/static/description/index.html
odoo/addons/crm_stage_type/tests/__init__.py
odoo/addons/crm_stage_type/tests/test_crm_stage_type.py
odoo/addons/crm_stage_type/views/crm_lead_views.xml
odoo/addons/crm_stage_type/views/crm_stage_views.xml
odoo13_addon_crm_stage_type-13.0.1.0.1.dist-info/METADATA
odoo13_addon_crm_stage_type-13.0.1.0.1.dist-info/WHEEL
odoo13_addon_crm_stage_type-13.0.1.0.1.dist-info/top_level.txt
odoo13_addon_crm_stage_type-13.0.1.0.1.dist-info/RECORD
